python_math1/__init__.py
python_math1-0.0.1.dist-info/METADATA
python_math1-0.0.1.dist-info/WHEEL
python_math1-0.0.1.dist-info/license.txt
python_math1-0.0.1.dist-info/top_level.txt
python_math1-0.0.1.dist-info/RECORD
