Metadata-Version: 2.1
Name: python-math1
Version: 0.0.1
Summary: function with numbers
Home-page: https://github.com/AkashKumarGit/
Author: Pranav Singh
Author-email: why_should_i_tell@gmail.com
License: UNKNOWN
Platform: UNKNOWN
Classifier: Programming Language :: Python :: 3
Classifier: License :: OSI Approved :: MIT License
Classifier: Operating System :: OS Independent
